buffy/__init__.py
buffy/buffypyclient/__init__.py
buffy/buffypyclient/buffypyclient.py
buffy/buffyserver/__init__.py
buffy/buffyserver/config.py
buffy/buffyserver/main.py
buffy/buffyserver/api/__init__.py
buffy/buffyserver/api/v1/__init__.py
buffy/buffyserver/api/v1/api.py
buffy/buffyserver/api/v1/models.py
buffy/buffyserver/api/v1/models_recaching_strategies.py
buffy/buffyserver/backend/storage_janitor.py
buffy/buffyserver/backend/tag_and_pin_manager.py
buffy/buffyserver/backend/request_download_service/__init__.py
buffy/buffyserver/backend/request_download_service/queue.py
buffy/buffyserver/backend/request_download_service/service.py
buffy/buffyserver/backend/storage/__init__.py
buffy/buffyserver/backend/storage/interface.py
buffy/buffyserver/backend/storage/redis_storage.py
buffy/tools/__init__.py
buffy/tools/stuborn_downloader.py
buffy/tools/utils.py
DZDBuffy-0.7.3.dist-info/LICENSE
DZDBuffy-0.7.3.dist-info/METADATA
DZDBuffy-0.7.3.dist-info/WHEEL
DZDBuffy-0.7.3.dist-info/entry_points.txt
DZDBuffy-0.7.3.dist-info/top_level.txt
DZDBuffy-0.7.3.dist-info/RECORD
