Metadata-Version: 2.1
Name: DZDBuffy
Version: 0.7.3
Summary: Versioning Caching kinda-Proxy for decoupling external responses
Home-page: https://git.connect.dzd-ev.de/dzdpythonmodules/buffy
Author: Tim Bleimehl
Author-email: tim.bleimehl@helmholtz-muenchen.de
License: MIT
Requires-Python: >=3.9
License-File: LICENSE
Requires-Dist: fastapi
Requires-Dist: uvicorn
Requires-Dist: pydantic
Requires-Dist: requests
Requires-Dist: redis
Requires-Dist: croniter
Requires-Dist: DZDConfigs
Requires-Dist: getversion
Requires-Dist: Click
Provides-Extra: docs
Requires-Dist: mkdocs ; extra == 'docs'
Requires-Dist: mkdocstrings[python] ; extra == 'docs'
Requires-Dist: mkdocs-autorefs ; extra == 'docs'
Requires-Dist: mkdocs-material ; extra == 'docs'
Requires-Dist: mkdocs-render-swagger-plugin ; extra == 'docs'
Provides-Extra: test
Requires-Dist: shittywebserver ; extra == 'test'
